ptah/__init__.py
ptah/cli/__init__.py
ptah/clients/__init__.py
ptah/clients/_injector.py
ptah/clients/caching.py
ptah/clients/dashboard.py
ptah/clients/docker.py
ptah/clients/filesystem.py
ptah/clients/forward.py
ptah/clients/helmfile.py
ptah/clients/kind.py
ptah/clients/kubernetes.py
ptah/clients/panic.py
ptah/clients/project.py
ptah/clients/shell.py
ptah/clients/ssh.py
ptah/clients/version.py
ptah/clients/yaml.py
ptah/clients/process/__init__.py
ptah/clients/process/__main__.py
ptah/models/__init__.py
ptah/models/constants.py
ptah/models/docker.py
ptah/models/kind.py
ptah/models/os.py
ptah/models/project.py
ptah/models/serialization.py
ptah/operations/__init__.py
ptah/operations/sync.py
ptah_cli-0.7.2.dist-info/LICENSE
ptah_cli-0.7.2.dist-info/METADATA
ptah_cli-0.7.2.dist-info/WHEEL
ptah_cli-0.7.2.dist-info/entry_points.txt
ptah_cli-0.7.2.dist-info/top_level.txt
ptah_cli-0.7.2.dist-info/RECORD
