Metadata-Version: 2.2
Name: ptah-cli
Version: 0.7.2
Author-email: Dan Miller <daniel.keegan.miller@gmail.com>
Requires-Python: <3.14,>=3.11
License-File: LICENSE
Requires-Dist: cachelib>=0.13.0
Requires-Dist: dirhash>=0.5.0
Requires-Dist: dockerfile-parse>=2.0.1
Requires-Dist: inflect>=7.4.0
Requires-Dist: injector>=0.21.0
Requires-Dist: jsonpath-ng>=1.7.0
Requires-Dist: omegaconf>=2.3.0
Requires-Dist: pathspec>=0.12.1
Requires-Dist: psutil>=6.1.0
Requires-Dist: pyperclip>=1.9.0
Requires-Dist: typer>=0.12.3
Requires-Dist: watchdog>=6.0.0
Provides-Extra: dev
Requires-Dist: build==1.2.2.post1; extra == "dev"
Requires-Dist: httpx==0.28.1; extra == "dev"
Requires-Dist: isort==6.0.0; extra == "dev"
Requires-Dist: pre-commit==4.1.0; extra == "dev"
Requires-Dist: pyright==1.1.393; extra == "dev"
Requires-Dist: pytest==8.3.4; extra == "dev"
Requires-Dist: pytest-cov==6.0.0; extra == "dev"
Requires-Dist: pytest-timeout==2.3.1; extra == "dev"
Requires-Dist: ruff==0.9.4; extra == "dev"
Provides-Extra: doc
Requires-Dist: mkdocs==1.6.1; extra == "doc"
Requires-Dist: mkdocs-click==0.8.1; extra == "doc"
Requires-Dist: mkdocs-material==9.6.1; extra == "doc"
